src/salesforce/__init__.py
src/salesforce/server.py
mseep_mcp_salesforce_connector-0.1.10.dist-info/METADATA
mseep_mcp_salesforce_connector-0.1.10.dist-info/WHEEL
mseep_mcp_salesforce_connector-0.1.10.dist-info/entry_points.txt
mseep_mcp_salesforce_connector-0.1.10.dist-info/licenses/LICENSE
mseep_mcp_salesforce_connector-0.1.10.dist-info/RECORD
